bigdata_research_tools/__init__.py
bigdata_research_tools/client.py
bigdata_research_tools/excel.py
bigdata_research_tools/labeler/__init__.py
bigdata_research_tools/labeler/labeler.py
bigdata_research_tools/labeler/narrative_labeler.py
bigdata_research_tools/labeler/risk_labeler.py
bigdata_research_tools/labeler/screener_labeler.py
bigdata_research_tools/llm/__init__.py
bigdata_research_tools/llm/azure.py
bigdata_research_tools/llm/base.py
bigdata_research_tools/llm/bedrock.py
bigdata_research_tools/llm/openai.py
bigdata_research_tools/llm/utils.py
bigdata_research_tools/portfolio/__init__.py
bigdata_research_tools/portfolio/motivation.py
bigdata_research_tools/portfolio/portfolio_constructor.py
bigdata_research_tools/prompts/__init__.py
bigdata_research_tools/prompts/labeler.py
bigdata_research_tools/prompts/motivation.py
bigdata_research_tools/prompts/risk.py
bigdata_research_tools/prompts/themes.py
bigdata_research_tools/res/bigdata-by-ravenpack-logo-dark.png
bigdata_research_tools/res/bigdata-by-ravenpack-logo.png
bigdata_research_tools/search/__init__.py
bigdata_research_tools/search/narrative_search.py
bigdata_research_tools/search/query_builder.py
bigdata_research_tools/search/screener_search.py
bigdata_research_tools/search/search.py
bigdata_research_tools/search/search_utils.py
bigdata_research_tools/settings.py
bigdata_research_tools/themes.py
bigdata_research_tools/tracing.py
bigdata_research_tools/utils/__init__.py
bigdata_research_tools/utils/distance.py
bigdata_research_tools/utils/observer.py
bigdata_research_tools/visuals/__init__.py
bigdata_research_tools/visuals/risk_visuals.py
bigdata_research_tools/visuals/thematic_visuals.py
bigdata_research_tools/visuals/visuals.py
bigdata_research_tools/watchlists.py
bigdata_research_tools/workflows/__init__.py
bigdata_research_tools/workflows/base.py
bigdata_research_tools/workflows/narrative_miner.py
bigdata_research_tools/workflows/risk_analyzer.py
bigdata_research_tools/workflows/thematic_screener.py
bigdata_research_tools-0.21.1.dist-info/WHEEL
bigdata_research_tools-0.21.1.dist-info/METADATA
bigdata_research_tools-0.21.1.dist-info/RECORD
