Metadata-Version: 2.3
Name: bigdata-research-tools
Version: 0.21.1
Summary: Bigdata.com API High-Efficiency Tools at Scale
Author: Bigdata.com
Author-email: Bigdata.com <support@ravenpack.com>
Requires-Dist: bigdata-client>=2.19.0
Requires-Dist: pandas>=2.2.3,<3.0.0
Requires-Dist: openpyxl>=3.1.5,<4.0.0
Requires-Dist: pillow>=11.1.0,<12.0.0
Requires-Dist: openai>=1.61.1,<2.0.0
Requires-Dist: graphviz>=0.20.3,<0.21.0
Requires-Dist: tqdm>=4.67.1
Requires-Dist: ipython>=8.0.0,<9.0.0
Requires-Dist: json-repair>=0.44.1
Requires-Dist: tabulate>=0.9.0,<1.0.0
Requires-Dist: plotly>=6.0.0,<7.0.0
Requires-Dist: azure-identity>=1.24.0 ; extra == 'azure'
Requires-Dist: openai>=1.61.1,<2.0.0 ; extra == 'azure'
Requires-Dist: boto3>=1.24.0,<2.0.0 ; extra == 'bedrock'
Requires-Dist: sphinx>=7.2.6 ; extra == 'docs'
Requires-Dist: autodoc-pydantic>=2.0.1 ; extra == 'docs'
Requires-Dist: myst-parser>=2.0.0 ; extra == 'docs'
Requires-Dist: furo>=2024.1.29 ; extra == 'docs'
Requires-Dist: sphinxcontrib-spelling>=8.0.0 ; extra == 'docs'
Requires-Dist: sphinx-new-tab-link>=0.6.0 ; extra == 'docs'
Requires-Dist: sphinx-copybutton>=0.5.2 ; extra == 'docs'
Requires-Dist: sphinx-reredirects>=0.1.5 ; extra == 'docs'
Requires-Dist: sphinx-togglebutton>=0.3.2 ; extra == 'docs'
Requires-Dist: openpyxl>=3.1.5,<4.0.0 ; extra == 'excel'
Requires-Dist: pillow>=11.1.0,<12.0.0 ; extra == 'excel'
Requires-Dist: graphviz>=0.20.3,<0.21.0 ; extra == 'graphviz'
Requires-Dist: openai>=1.61.1,<2.0.0 ; extra == 'openai'
Requires-Dist: plotly>=6.0.0,<7.0.0 ; extra == 'plotly'
Requires-Python: >=3.9, <4.0
Project-URL: homepage, https://bigdata.com/api
Provides-Extra: azure
Provides-Extra: bedrock
Provides-Extra: docs
Provides-Extra: excel
Provides-Extra: graphviz
Provides-Extra: openai
Provides-Extra: plotly
